{
    "admin/fs_web_ranking_addEdit.html": {
        "version_id": 1000010,
        "version_string": "1.0.0 Alpha",
        "hash": "d19542d504cb1ba004eef1785553651e"
    },
    "admin/fs_web_ranking_index.html": {
        "version_id": 1000010,
        "version_string": "1.0.0 Alpha",
        "hash": "97a13907b90b0ae20be78245610e93b6"
    },
    "public/fs_web_ranking_css_helper.less": {
        "version_id": 1000010,
        "version_string": "1.0.0 Alpha",
        "hash": "fcb6d323f2274e994286061ebcc233ae"
    },
    "public/fs_web_ranking_grid_card.less": {
        "version_id": 1000010,
        "version_string": "1.0.0 Alpha",
        "hash": "98374849beda25f296c2bacdc7445647"
    },
    "public/fs_web_ranking_index.html": {
        "version_id": 1000010,
        "version_string": "1.0.0 Alpha",
        "hash": "06224989fda630f0810c5f472ab501c5"
    },
    "public/fs_web_ranking_list.less": {
        "version_id": 1000010,
        "version_string": "1.0.0 Alpha",
        "hash": "82a1c70b114b5834518f4551cd013d73"
    },
    "public/fs_web_ranking_solved.html": {
        "version_id": 1000010,
        "version_string": "1.0.0 Alpha",
        "hash": "79e1264679cd622100a7c6500df795f0"
    },
    "public/fs_web_ranking_style.less": {
        "version_id": 1000010,
        "version_string": "1.0.0 Alpha",
        "hash": "dcea42e4574857c4d14ddde514dc76fc"
    },
    "public/fs_wesite_ranking_status.html": {
        "version_id": 1000010,
        "version_string": "1.0.0 Alpha",
        "hash": "b472d343de34b8a8f1f5851613f51738"
    },
    "public/fs_wesite_ranking_status_css.less": {
        "version_id": 1000010,
        "version_string": "1.0.0 Alpha",
        "hash": "a35f058a1ce436acc36ac50cb3e902a0"
    }
}